buf/__init__.py
buf/validate/__init__.py
buf/validate/validate_grpc.py
buf/validate/validate_pb2.py
buf/validate/validate_pb2.pyi
google/__init__.py
google/api/__init__.py
google/api/annotations_grpc.py
google/api/annotations_pb2.py
google/api/annotations_pb2.pyi
google/api/http_grpc.py
google/api/http_pb2.py
google/api/http_pb2.pyi
grpcoauth/__init__.py
grpcoauth/v1/__init__.py
grpcoauth/v1/enums_grpc.py
grpcoauth/v1/enums_pb2.py
grpcoauth/v1/enums_pb2.pyi
grpcoauth/v1/oauth_grpc.py
grpcoauth/v1/oauth_pb2.py
grpcoauth/v1/oauth_pb2.pyi
grpcoauth/v1/user_grpc.py
grpcoauth/v1/user_pb2.py
grpcoauth/v1/user_pb2.pyi
grpc_oauth_vet1ments-2.0.41.dist-info/METADATA
grpc_oauth_vet1ments-2.0.41.dist-info/WHEEL
grpc_oauth_vet1ments-2.0.41.dist-info/top_level.txt
grpc_oauth_vet1ments-2.0.41.dist-info/RECORD
