Metadata-Version: 2.1
Name: grpc-oauth-vet1ments
Version: 2.0.41
Summary: assistant proto
Home-page: https://github.com/vet1ments/grpc-oauth-python.git
Author: vet1ments
Author-email: vet1ments@naver.com
Requires-Python: >=3.11
